README.rst
setup.py
Poogle.egg-info/PKG-INFO
Poogle.egg-info/SOURCES.txt
Poogle.egg-info/dependency_links.txt
Poogle.egg-info/entry_points.txt
Poogle.egg-info/requires.txt
Poogle.egg-info/top_level.txt
poogle/__init__.py
poogle/containers.py
poogle/errors.py
poogle/cli/__init__.py
poogle/cli/search.py