Metadata-Version: 1.1
Name: Poogle
Version: 0.1.0
Summary: Poogle is a Google scraping library and command line utility for Python.
Home-page: https://github.com/FujiMakoto/Poogle
Author: Makoto Fujimoto
Author-email: makoto@makoto.io
License: MIT
Keywords: google,web search,search engine
Platform: UNKNOWN
Classifier: Development Status :: 2 - Pre-Alpha
Classifier: License :: OSI Approved :: MIT License
Classifier: Environment :: Console
Classifier: Intended Audience :: Developers
Classifier: Intended Audience :: End Users/Desktop
Classifier: Programming Language :: Python :: 2.7
Classifier: Programming Language :: Python :: 3.3
Classifier: Programming Language :: Python :: 3.4
Classifier: Programming Language :: Python :: 3.5
Classifier: Topic :: Internet :: WWW/HTTP :: Indexing/Search
Classifier: Topic :: Software Development :: Libraries
Classifier: Topic :: Utilities
